django3_saml2_nbplugin/__init__.py
django3_saml2_nbplugin/backends.py
django3_saml2_nbplugin/api/__init__.py
django3_saml2_nbplugin/api/urls.py
netbox_plugin_auth_saml2-3.0.dist-info/METADATA
netbox_plugin_auth_saml2-3.0.dist-info/WHEEL
netbox_plugin_auth_saml2-3.0.dist-info/top_level.txt
netbox_plugin_auth_saml2-3.0.dist-info/RECORD
