Metadata-Version: 2.1
Name: netbox-plugin-auth-saml2
Version: 3.0
Summary: Netbox plugin for SAML2 auth
Author: Jeremy Schulman
License: Apache 2.0
